ttwidgets/__init__.py
ttwidgets/ttwidgets.py
ttwidgets/test/__init__.py
ttwidgets/test/test_ttwidgets.py
ttwidgets-1.1.3.dist-info/LICENSE.txt
ttwidgets-1.1.3.dist-info/METADATA
ttwidgets-1.1.3.dist-info/NOTICE.txt
ttwidgets-1.1.3.dist-info/WHEEL
ttwidgets-1.1.3.dist-info/top_level.txt
ttwidgets-1.1.3.dist-info/RECORD
