Metadata-Version: 2.1
Name: ttwidgets
Version: 1.1.3
Summary: Improved Tkinter widgets that accept HTML-like tagged text to support multiple fonts and enhanced visual schemes.
Home-page: https://github.com/GaryBloom/ttwidgets
Author: Gary Michael Bloom
Author-email: bloominator@hotmail.com
License: Apache License 2.0
Classifier: License :: OSI Approved :: Apache Software License
Classifier: Operating System :: OS Independent
Classifier: Programming Language :: Python :: 3
Classifier: Programming Language :: Python :: 3.5
Classifier: Programming Language :: Python :: 3.6
Classifier: Programming Language :: Python :: 3.7
Classifier: Programming Language :: Python :: 3.8
Classifier: Programming Language :: Python :: 3.9
Classifier: Programming Language :: Python :: 3.10
Classifier: Programming Language :: Python :: 3.11
Requires-Python: >=3.5
License-File: LICENSE.txt
License-File: NOTICE.txt
